{"symbol": "MRVL", "annualReports": [{"fiscalDateEnding": "2021-02-28", "reportedCurrency": "USD", "operatingCashflow": "817287000", "paymentsForOperatingActivities": "None", "proceedsFromOperatingActivities": "None", "changeInOperatingLiabilities": "None", "changeInOperatingAssets": "None", "depreciationDepletionAndAmortization": "641528000", "capitalExpenditures": "119506000", "changeInReceivables": "None", "changeInInventory": "29913000", "profitLoss": "None", "cashflowFromInvestment": "-119644000", "cashflowFromFinancing": "-596780000", "proceedsFromRepaymentsOfShortTermDebt": "None", "paymentsForRepurchaseOfCommonStock": "None", "paymentsForRepurchaseOfEquity": "None", "paymentsForRepurchaseOfPreferredStock": "None", "dividendPayout": "160574000", "dividendPayoutCommonStock": "160574000", "dividendPayoutPreferredStock": "None", "proceedsFromIssuanceOfCommonStock": "None", "proceedsFromIssuanceOfLongTermDebtAndCapitalSecuritiesNet": "None", "proceedsFromIssuanceOfPreferredStock": "None", "proceedsFromRepurchaseOfEquity": "-25202000", "proceedsFromSaleOfTreasuryStock": "None", "changeInCashAndCashEquivalents": "None", "changeInExchangeRate": "None", "netIncome": "-277298000"}, {"fiscalDateEnding": "2020-02-29", "reportedCurrency": "USD", "operatingCashflow": "360297000", "paymentsForOperatingActivities": "None", "proceedsFromOperatingActivities": "None", "changeInOperatingLiabilities": "None", "changeInOperatingAssets": "None", "depreciationDepletionAndAmortization": "524740000", "capitalExpenditures": "86633000", "changeInReceivables": "11244000", "changeInInventory": "12759000", "profitLoss": "None", "cashflowFromInvestment": "558846000", "cashflowFromFinancing": "-853949000", "proceedsFromRepaymentsOfShortTermDebt": "None", "paymentsForRepurchaseOfCommonStock": "None", "paymentsForRepurchaseOfEquity": "None", "paymentsForRepurchaseOfPreferredStock": "None", "dividendPayout": "159573000", "dividendPayoutCommonStock": "159573000", "dividendPayoutPreferredStock": "None", "proceedsFromIssuanceOfCommonStock": "None", "proceedsFromIssuanceOfLongTermDebtAndCapitalSecuritiesNet": "None", "proceedsFromIssuanceOfPreferredStock": "None", "proceedsFromRepurchaseOfEquity": "-364272000", "proceedsFromSaleOfTreasuryStock": "None", "changeInCashAndCashEquivalents": "65194000", "changeInExchangeRate": "None", "netIncome": "1584391000"}, {"fiscalDateEnding": "2019-02-28", "reportedCurrency": "USD", "operatingCashflow": "596744000", "paymentsForOperatingActivities": "None", "proceedsFromOperatingActivities": "None", "changeInOperatingLiabilities": "None", "changeInOperatingAssets": "None", "depreciationDepletionAndAmortization": "307301000", "capitalExpenditures": "87461000", "changeInReceivables": "-99044000", "changeInInventory": "4348000", "profitLoss": "None", "cashflowFromInvestment": "-1752553000", "cashflowFromFinancing": "849737000", "proceedsFromRepaymentsOfShortTermDebt": "None", "paymentsForRepurchaseOfCommonStock": "None", "paymentsForRepurchaseOfEquity": "None", "paymentsForRepurchaseOfPreferredStock": "None", "dividendPayout": "148081000", "dividendPayoutCommonStock": "148081000", "dividendPayoutPreferredStock": "None", "proceedsFromIssuanceOfCommonStock": "None", "proceedsFromIssuanceOfLongTermDebtAndCapitalSecuritiesNet": "None", "proceedsFromIssuanceOfPreferredStock": "None", "proceedsFromRepurchaseOfEquity": "-103974000", "proceedsFromSaleOfTreasuryStock": "None", "changeInCashAndCashEquivalents": "-306072000", "changeInExchangeRate": "None", "netIncome": "-179094000"}, {"fiscalDateEnding": "2018-02-28", "reportedCurrency": "USD", "operatingCashflow": "571113000", "paymentsForOperatingActivities": "None", "proceedsFromOperatingActivities": "None", "changeInOperatingLiabilities": "None", "changeInOperatingAssets": "None", "depreciationDepletionAndAmortization": "87057000", "capitalExpenditures": "45138000", "changeInReceivables": "None", "changeInInventory": "-12160000", "profitLoss": "None", "cashflowFromInvestment": "39521000", "cashflowFromFinancing": "-536244000", "proceedsFromRepaymentsOfShortTermDebt": "None", "paymentsForRepurchaseOfCommonStock": "None", "paymentsForRepurchaseOfEquity": "None", "paymentsForRepurchaseOfPreferredStock": "None", "dividendPayout": "119251000", "dividendPayoutCommonStock": "119251000", "dividendPayoutPreferredStock": "None", "proceedsFromIssuanceOfCommonStock": "None", "proceedsFromIssuanceOfLongTermDebtAndCapitalSecuritiesNet": "None", "proceedsFromIssuanceOfPreferredStock": "None", "proceedsFromRepurchaseOfEquity": "-527574000", "proceedsFromSaleOfTreasuryStock": "None", "changeInCashAndCashEquivalents": "None", "changeInExchangeRate": "None", "netIncome": "432425000"}, {"fiscalDateEnding": "2017-02-28", "reportedCurrency": "USD", "operatingCashflow": "-358435000", "paymentsForOperatingActivities": "None", "proceedsFromOperatingActivities": "None", "changeInOperatingLiabilities": "None", "changeInOperatingAssets": "None", "depreciationDepletionAndAmortization": "118492000", "capitalExpenditures": "44510000", "changeInReceivables": "-12084000", "changeInInventory": "29325000", "profitLoss": "None", "cashflowFromInvestment": "161595000", "cashflowFromFinancing": "-267248000", "proceedsFromRepaymentsOfShortTermDebt": "None", "paymentsForRepurchaseOfCommonStock": "None", "paymentsForRepurchaseOfEquity": "None", "paymentsForRepurchaseOfPreferredStock": "None", "dividendPayout": "122292000", "dividendPayoutCommonStock": "122292000", "dividendPayoutPreferredStock": "None", "proceedsFromIssuanceOfCommonStock": "None", "proceedsFromIssuanceOfLongTermDebtAndCapitalSecuritiesNet": "None", "proceedsFromIssuanceOfPreferredStock": "None", "proceedsFromRepurchaseOfEquity": "-107345000", "proceedsFromSaleOfTreasuryStock": "None", "changeInCashAndCashEquivalents": "-464088000", "changeInExchangeRate": "None", "netIncome": "21151000"}], "quarterlyReports": [{"fiscalDateEnding": "2021-05-31", "reportedCurrency": "USD", "operatingCashflow": "-13727000", "paymentsForOperatingActivities": "None", "proceedsFromOperatingActivities": "None", "changeInOperatingLiabilities": "None", "changeInOperatingAssets": "None", "depreciationDepletionAndAmortization": "180476000", "capitalExpenditures": "24887000", "changeInReceivables": "None", "changeInInventory": "-13249000", "profitLoss": "None", "cashflowFromInvestment": "-3624605000", "cashflowFromFinancing": "3412377000", "proceedsFromRepaymentsOfShortTermDebt": "None", "paymentsForRepurchaseOfCommonStock": "None", "paymentsForRepurchaseOfEquity": "None", "paymentsForRepurchaseOfPreferredStock": "None", "dividendPayout": "40557000", "dividendPayoutCommonStock": "40557000", "dividendPayoutPreferredStock": "None", "proceedsFromIssuanceOfCommonStock": "None", "proceedsFromIssuanceOfLongTermDebtAndCapitalSecuritiesNet": "None", "proceedsFromIssuanceOfPreferredStock": "None", "proceedsFromRepurchaseOfEquity": "0", "proceedsFromSaleOfTreasuryStock": "None", "changeInCashAndCashEquivalents": "None", "changeInExchangeRate": "None", "netIncome": "-88242000"}, {"fiscalDateEnding": "2021-02-28", "reportedCurrency": "USD", "operatingCashflow": "158295000", "paymentsForOperatingActivities": "None", "proceedsFromOperatingActivities": "None", "changeInOperatingLiabilities": "None", "changeInOperatingAssets": "None", "depreciationDepletionAndAmortization": "157672000", "capitalExpenditures": "22788000", "changeInReceivables": "None", "changeInInventory": "96000", "profitLoss": "None", "cashflowFromInvestment": "None", "cashflowFromFinancing": "-218720000", "proceedsFromRepaymentsOfShortTermDebt": "None", "paymentsForRepurchaseOfCommonStock": "None", "paymentsForRepurchaseOfEquity": "None", "paymentsForRepurchaseOfPreferredStock": "None", "dividendPayout": "40463000", "dividendPayoutCommonStock": "40463000", "dividendPayoutPreferredStock": "None", "proceedsFromIssuanceOfCommonStock": "None", "proceedsFromIssuanceOfLongTermDebtAndCapitalSecuritiesNet": "None", "proceedsFromIssuanceOfPreferredStock": "None", "proceedsFromRepurchaseOfEquity": "0", "proceedsFromSaleOfTreasuryStock": "None", "changeInCashAndCashEquivalents": "None", "changeInExchangeRate": "None", "netIncome": "16536000"}, {"fiscalDateEnding": "2020-11-30", "reportedCurrency": "USD", "operatingCashflow": "257534000", "paymentsForOperatingActivities": "None", "proceedsFromOperatingActivities": "None", "changeInOperatingLiabilities": "None", "changeInOperatingAssets": "None", "depreciationDepletionAndAmortization": "157267000", "capitalExpenditures": "37071000", "changeInReceivables": "None", "changeInInventory": "-5984000", "profitLoss": "None", "cashflowFromInvestment": "-23149000", "cashflowFromFinancing": "-219480000", "proceedsFromRepaymentsOfShortTermDebt": "None", "paymentsForRepurchaseOfCommonStock": "None", "paymentsForRepurchaseOfEquity": "None", "paymentsForRepurchaseOfPreferredStock": "None", "dividendPayout": "40229000", "dividendPayoutCommonStock": "40229000", "dividendPayoutPreferredStock": "None", "proceedsFromIssuanceOfCommonStock": "None", "proceedsFromIssuanceOfLongTermDebtAndCapitalSecuritiesNet": "None", "proceedsFromIssuanceOfPreferredStock": "None", "proceedsFromRepurchaseOfEquity": "-25202000", "proceedsFromSaleOfTreasuryStock": "None", "changeInCashAndCashEquivalents": "None", "changeInExchangeRate": "None", "netIncome": "-22908000"}, {"fiscalDateEnding": "2020-08-31", "reportedCurrency": "USD", "operatingCashflow": "225830000", "paymentsForOperatingActivities": "None", "proceedsFromOperatingActivities": "None", "changeInOperatingLiabilities": "None", "changeInOperatingAssets": "None", "depreciationDepletionAndAmortization": "163184000", "capitalExpenditures": "20620000", "changeInReceivables": "-6729000", "changeInInventory": "-33000", "profitLoss": "None", "cashflowFromInvestment": "-37547000", "cashflowFromFinancing": "-41258000", "proceedsFromRepaymentsOfShortTermDebt": "None", "paymentsForRepurchaseOfCommonStock": "None", "paymentsForRepurchaseOfEquity": "None", "paymentsForRepurchaseOfPreferredStock": "None", "dividendPayout": "40119000", "dividendPayoutCommonStock": "40119000", "dividendPayoutPreferredStock": "None", "proceedsFromIssuanceOfCommonStock": "None", "proceedsFromIssuanceOfLongTermDebtAndCapitalSecuritiesNet": "None", "proceedsFromIssuanceOfPreferredStock": "None", "proceedsFromRepurchaseOfEquity": "42776000", "proceedsFromSaleOfTreasuryStock": "None", "changeInCashAndCashEquivalents": "507000", "changeInExchangeRate": "None", "netIncome": "-157893000"}, {"fiscalDateEnding": "2020-05-31", "reportedCurrency": "USD", "operatingCashflow": "225830000", "paymentsForOperatingActivities": "None", "proceedsFromOperatingActivities": "None", "changeInOperatingLiabilities": "None", "changeInOperatingAssets": "None", "depreciationDepletionAndAmortization": "163184000", "capitalExpenditures": "20620000", "changeInReceivables": "23586000", "changeInInventory": "-33000", "profitLoss": "None", "cashflowFromInvestment": "-38362000", "cashflowFromFinancing": "-41258000", "proceedsFromRepaymentsOfShortTermDebt": "None", "paymentsForRepurchaseOfCommonStock": "None", "paymentsForRepurchaseOfEquity": "None", "paymentsForRepurchaseOfPreferredStock": "None", "dividendPayout": "40119000", "dividendPayoutCommonStock": "40119000", "dividendPayoutPreferredStock": "None", "proceedsFromIssuanceOfCommonStock": "None", "proceedsFromIssuanceOfLongTermDebtAndCapitalSecuritiesNet": "None", "proceedsFromIssuanceOfPreferredStock": "None", "proceedsFromRepurchaseOfEquity": "-19744000", "proceedsFromSaleOfTreasuryStock": "None", "changeInCashAndCashEquivalents": "19944000", "changeInExchangeRate": "None", "netIncome": "-157893000"}, {"fiscalDateEnding": "2020-02-29", "reportedCurrency": "USD", "operatingCashflow": "55838000", "paymentsForOperatingActivities": "None", "proceedsFromOperatingActivities": "None", "changeInOperatingLiabilities": "None", "changeInOperatingAssets": "None", "depreciationDepletionAndAmortization": "144526000", "capitalExpenditures": "18986000", "changeInReceivables": "2870000", "changeInInventory": "43361000", "profitLoss": "None", "cashflowFromInvestment": "1084257000", "cashflowFromFinancing": "-930860000", "proceedsFromRepaymentsOfShortTermDebt": "None", "paymentsForRepurchaseOfCommonStock": "None", "paymentsForRepurchaseOfEquity": "None", "paymentsForRepurchaseOfPreferredStock": "None", "dividendPayout": "40077000", "dividendPayoutCommonStock": "40077000", "dividendPayoutPreferredStock": "None", "proceedsFromIssuanceOfCommonStock": "None", "proceedsFromIssuanceOfLongTermDebtAndCapitalSecuritiesNet": "None", "proceedsFromIssuanceOfPreferredStock": "None", "proceedsFromRepurchaseOfEquity": "-255833000", "proceedsFromSaleOfTreasuryStock": "None", "changeInCashAndCashEquivalents": "209235000", "changeInExchangeRate": "None", "netIncome": "1772673000"}, {"fiscalDateEnding": "2019-11-30", "reportedCurrency": "USD", "operatingCashflow": "65503000", "paymentsForOperatingActivities": "None", "proceedsFromOperatingActivities": "None", "changeInOperatingLiabilities": "None", "changeInOperatingAssets": "None", "depreciationDepletionAndAmortization": "133268000", "capitalExpenditures": "20742000", "changeInReceivables": "-32002000", "changeInInventory": "-39276000", "profitLoss": "None", "cashflowFromInvestment": "-481307000", "cashflowFromFinancing": "280677000", "proceedsFromRepaymentsOfShortTermDebt": "None", "paymentsForRepurchaseOfCommonStock": "None", "paymentsForRepurchaseOfEquity": "None", "paymentsForRepurchaseOfPreferredStock": "None", "dividendPayout": "40140000", "dividendPayoutCommonStock": "40140000", "dividendPayoutPreferredStock": "None", "proceedsFromIssuanceOfCommonStock": "None", "proceedsFromIssuanceOfLongTermDebtAndCapitalSecuritiesNet": "None", "proceedsFromIssuanceOfPreferredStock": "None", "proceedsFromRepurchaseOfEquity": "21795000", "proceedsFromSaleOfTreasuryStock": "None", "changeInCashAndCashEquivalents": "-135127000", "changeInExchangeRate": "None", "netIncome": "-82501000"}, {"fiscalDateEnding": "2019-08-31", "reportedCurrency": "USD", "operatingCashflow": "73140000", "paymentsForOperatingActivities": "None", "proceedsFromOperatingActivities": "None", "changeInOperatingLiabilities": "None", "changeInOperatingAssets": "None", "depreciationDepletionAndAmortization": "122908000", "capitalExpenditures": "23010000", "changeInReceivables": "17601000", "changeInInventory": "-7174000", "profitLoss": "None", "cashflowFromInvestment": "-23095000", "cashflowFromFinancing": "-48442000", "proceedsFromRepaymentsOfShortTermDebt": "None", "paymentsForRepurchaseOfCommonStock": "None", "paymentsForRepurchaseOfEquity": "None", "paymentsForRepurchaseOfPreferredStock": "None", "dividendPayout": "39889000", "dividendPayoutCommonStock": "39889000", "dividendPayoutPreferredStock": "None", "proceedsFromIssuanceOfCommonStock": "None", "proceedsFromIssuanceOfLongTermDebtAndCapitalSecuritiesNet": "None", "proceedsFromIssuanceOfPreferredStock": "None", "proceedsFromRepurchaseOfEquity": "33980000", "proceedsFromSaleOfTreasuryStock": "None", "changeInCashAndCashEquivalents": "1603000", "changeInExchangeRate": "None", "netIncome": "-57331000"}, {"fiscalDateEnding": "2019-05-31", "reportedCurrency": "USD", "operatingCashflow": "165816000", "paymentsForOperatingActivities": "None", "proceedsFromOperatingActivities": "None", "changeInOperatingLiabilities": "None", "changeInOperatingAssets": "None", "depreciationDepletionAndAmortization": "124038000", "capitalExpenditures": "19183000", "changeInReceivables": "22775000", "changeInInventory": "15848000", "profitLoss": "None", "cashflowFromInvestment": "-21009000", "cashflowFromFinancing": "-155324000", "proceedsFromRepaymentsOfShortTermDebt": "None", "paymentsForRepurchaseOfCommonStock": "None", "paymentsForRepurchaseOfEquity": "None", "paymentsForRepurchaseOfPreferredStock": "None", "dividendPayout": "39467000", "dividendPayoutCommonStock": "39467000", "dividendPayoutPreferredStock": "None", "proceedsFromIssuanceOfCommonStock": "None", "proceedsFromIssuanceOfLongTermDebtAndCapitalSecuritiesNet": "None", "proceedsFromIssuanceOfPreferredStock": "None", "proceedsFromRepurchaseOfEquity": "-16938000", "proceedsFromSaleOfTreasuryStock": "None", "changeInCashAndCashEquivalents": "-10517000", "changeInExchangeRate": "None", "netIncome": "-48450000"}, {"fiscalDateEnding": "2019-02-28", "reportedCurrency": "None", "operatingCashflow": "106641000", "paymentsForOperatingActivities": "None", "proceedsFromOperatingActivities": "None", "changeInOperatingLiabilities": "None", "changeInOperatingAssets": "None", "depreciationDepletionAndAmortization": "116315000", "capitalExpenditures": "28886000", "changeInReceivables": "None", "changeInInventory": "2489000", "profitLoss": "None", "cashflowFromInvestment": "None", "cashflowFromFinancing": "-150229000", "proceedsFromRepaymentsOfShortTermDebt": "None", "paymentsForRepurchaseOfCommonStock": "None", "paymentsForRepurchaseOfEquity": "None", "paymentsForRepurchaseOfPreferredStock": "None", "dividendPayout": "39489000", "dividendPayoutCommonStock": "39489000", "dividendPayoutPreferredStock": "None", "proceedsFromIssuanceOfCommonStock": "None", "proceedsFromIssuanceOfLongTermDebtAndCapitalSecuritiesNet": "None", "proceedsFromIssuanceOfPreferredStock": "None", "proceedsFromRepurchaseOfEquity": "-9816000", "proceedsFromSaleOfTreasuryStock": "None", "changeInCashAndCashEquivalents": "None", "changeInExchangeRate": "None", "netIncome": "-260698000"}, {"fiscalDateEnding": "2018-11-30", "reportedCurrency": "USD", "operatingCashflow": "299403000", "paymentsForOperatingActivities": "None", "proceedsFromOperatingActivities": "None", "changeInOperatingLiabilities": "None", "changeInOperatingAssets": "None", "depreciationDepletionAndAmortization": "117986000", "capitalExpenditures": "12646000", "changeInReceivables": "None", "changeInInventory": "-5007000", "profitLoss": "None", "cashflowFromInvestment": "-1571000", "cashflowFromFinancing": "-186234000", "proceedsFromRepaymentsOfShortTermDebt": "None", "paymentsForRepurchaseOfCommonStock": "None", "paymentsForRepurchaseOfEquity": "None", "paymentsForRepurchaseOfPreferredStock": "None", "dividendPayout": "39392000", "dividendPayoutCommonStock": "39392000", "dividendPayoutPreferredStock": "None", "proceedsFromIssuanceOfCommonStock": "None", "proceedsFromIssuanceOfLongTermDebtAndCapitalSecuritiesNet": "None", "proceedsFromIssuanceOfPreferredStock": "None", "proceedsFromRepurchaseOfEquity": "-37797000", "proceedsFromSaleOfTreasuryStock": "None", "changeInCashAndCashEquivalents": "None", "changeInExchangeRate": "None", "netIncome": "-53767000"}, {"fiscalDateEnding": "2018-08-31", "reportedCurrency": "USD", "operatingCashflow": "61900000", "paymentsForOperatingActivities": "None", "proceedsFromOperatingActivities": "None", "changeInOperatingLiabilities": "None", "changeInOperatingAssets": "None", "depreciationDepletionAndAmortization": "52700000", "capitalExpenditures": "34389000", "changeInReceivables": "None", "changeInInventory": "6866000", "profitLoss": "None", "cashflowFromInvestment": "-1983418000", "cashflowFromFinancing": "1252900000", "proceedsFromRepaymentsOfShortTermDebt": "None", "paymentsForRepurchaseOfCommonStock": "None", "paymentsForRepurchaseOfEquity": "None", "paymentsForRepurchaseOfPreferredStock": "None", "dividendPayout": "39400000", "dividendPayoutCommonStock": "39400000", "dividendPayoutPreferredStock": "None", "proceedsFromIssuanceOfCommonStock": "None", "proceedsFromIssuanceOfLongTermDebtAndCapitalSecuritiesNet": "None", "proceedsFromIssuanceOfPreferredStock": "None", "proceedsFromRepurchaseOfEquity": "33500000", "proceedsFromSaleOfTreasuryStock": "None", "changeInCashAndCashEquivalents": "None", "changeInExchangeRate": "None", "netIncome": "6800000"}, {"fiscalDateEnding": "2018-05-31", "reportedCurrency": "USD", "operatingCashflow": "128800000", "paymentsForOperatingActivities": "None", "proceedsFromOperatingActivities": "None", "changeInOperatingLiabilities": "None", "changeInOperatingAssets": "None", "depreciationDepletionAndAmortization": "20300000", "capitalExpenditures": "13900000", "changeInReceivables": "-47393000", "changeInInventory": "2680000", "profitLoss": "None", "cashflowFromInvestment": "216699000", "cashflowFromFinancing": "-66700000", "proceedsFromRepaymentsOfShortTermDebt": "None", "paymentsForRepurchaseOfCommonStock": "None", "paymentsForRepurchaseOfEquity": "None", "paymentsForRepurchaseOfPreferredStock": "None", "dividendPayout": "29800000", "dividendPayoutCommonStock": "29800000", "dividendPayoutPreferredStock": "None", "proceedsFromIssuanceOfCommonStock": "None", "proceedsFromIssuanceOfLongTermDebtAndCapitalSecuritiesNet": "None", "proceedsFromIssuanceOfPreferredStock": "None", "proceedsFromRepurchaseOfEquity": "11100000", "proceedsFromSaleOfTreasuryStock": "None", "changeInCashAndCashEquivalents": "278776000", "changeInExchangeRate": "None", "netIncome": "128600000"}, {"fiscalDateEnding": "2018-02-28", "reportedCurrency": "USD", "operatingCashflow": "119700000", "paymentsForOperatingActivities": "None", "proceedsFromOperatingActivities": "None", "changeInOperatingLiabilities": "None", "changeInOperatingAssets": "None", "depreciationDepletionAndAmortization": "21300000", "capitalExpenditures": "13588000", "changeInReceivables": "-47393000", "changeInInventory": "2680000", "profitLoss": "None", "cashflowFromInvestment": "216699000", "cashflowFromFinancing": "-7900000", "proceedsFromRepaymentsOfShortTermDebt": "None", "paymentsForRepurchaseOfCommonStock": "None", "paymentsForRepurchaseOfEquity": "None", "paymentsForRepurchaseOfPreferredStock": "None", "dividendPayout": "29700000", "dividendPayoutCommonStock": "29700000", "dividendPayoutPreferredStock": "None", "proceedsFromIssuanceOfCommonStock": "None", "proceedsFromIssuanceOfLongTermDebtAndCapitalSecuritiesNet": "None", "proceedsFromIssuanceOfPreferredStock": "None", "proceedsFromRepurchaseOfEquity": "42900000", "proceedsFromSaleOfTreasuryStock": "None", "changeInCashAndCashEquivalents": "278776000", "changeInExchangeRate": "None", "netIncome": "48800000"}, {"fiscalDateEnding": "2017-11-30", "reportedCurrency": "None", "operatingCashflow": "216200000", "paymentsForOperatingActivities": "None", "proceedsFromOperatingActivities": "None", "changeInOperatingLiabilities": "None", "changeInOperatingAssets": "None", "depreciationDepletionAndAmortization": "22500000", "capitalExpenditures": "11110000", "changeInReceivables": "None", "changeInInventory": "-1327000", "profitLoss": "None", "cashflowFromInvestment": "None", "cashflowFromFinancing": "-139400000", "proceedsFromRepaymentsOfShortTermDebt": "None", "paymentsForRepurchaseOfCommonStock": "None", "paymentsForRepurchaseOfEquity": "None", "paymentsForRepurchaseOfPreferredStock": "None", "dividendPayout": "29500000", "dividendPayoutCommonStock": "29500000", "dividendPayoutPreferredStock": "None", "proceedsFromIssuanceOfCommonStock": "None", "proceedsFromIssuanceOfLongTermDebtAndCapitalSecuritiesNet": "None", "proceedsFromIssuanceOfPreferredStock": "None", "proceedsFromRepurchaseOfEquity": "-100500000", "proceedsFromSaleOfTreasuryStock": "None", "changeInCashAndCashEquivalents": "None", "changeInExchangeRate": "None", "netIncome": "200200000"}, {"fiscalDateEnding": "2017-08-31", "reportedCurrency": "USD", "operatingCashflow": "101000000", "paymentsForOperatingActivities": "None", "proceedsFromOperatingActivities": "None", "changeInOperatingLiabilities": "None", "changeInOperatingAssets": "None", "depreciationDepletionAndAmortization": "21500000", "capitalExpenditures": "4020000", "changeInReceivables": "5583000", "changeInInventory": "-3170000", "profitLoss": "None", "cashflowFromInvestment": "94019000", "cashflowFromFinancing": "-183900000", "proceedsFromRepaymentsOfShortTermDebt": "None", "paymentsForRepurchaseOfCommonStock": "None", "paymentsForRepurchaseOfEquity": "None", "paymentsForRepurchaseOfPreferredStock": "None", "dividendPayout": "30100000", "dividendPayoutCommonStock": "30100000", "dividendPayoutPreferredStock": "None", "proceedsFromIssuanceOfCommonStock": "None", "proceedsFromIssuanceOfLongTermDebtAndCapitalSecuritiesNet": "None", "proceedsFromIssuanceOfPreferredStock": "None", "proceedsFromRepurchaseOfEquity": "-143300000", "proceedsFromSaleOfTreasuryStock": "None", "changeInCashAndCashEquivalents": "169598000", "changeInExchangeRate": "None", "netIncome": "165300000"}, {"fiscalDateEnding": "2017-05-31", "reportedCurrency": "USD", "operatingCashflow": "134200000", "paymentsForOperatingActivities": "None", "proceedsFromOperatingActivities": "None", "changeInOperatingLiabilities": "None", "changeInOperatingAssets": "None", "depreciationDepletionAndAmortization": "21800000", "capitalExpenditures": "10026000", "changeInReceivables": "-14550000", "changeInInventory": "-11542000", "profitLoss": "None", "cashflowFromInvestment": "-12739000", "cashflowFromFinancing": "-205000000", "proceedsFromRepaymentsOfShortTermDebt": "None", "paymentsForRepurchaseOfCommonStock": "None", "paymentsForRepurchaseOfEquity": "None", "paymentsForRepurchaseOfPreferredStock": "None", "dividendPayout": "30000000", "dividendPayoutCommonStock": "30000000", "dividendPayoutPreferredStock": "None", "proceedsFromIssuanceOfCommonStock": "None", "proceedsFromIssuanceOfLongTermDebtAndCapitalSecuritiesNet": "None", "proceedsFromIssuanceOfPreferredStock": "None", "proceedsFromRepurchaseOfEquity": "-146400000", "proceedsFromSaleOfTreasuryStock": "None", "changeInCashAndCashEquivalents": "-95461000", "changeInExchangeRate": "None", "netIncome": "106600000"}, {"fiscalDateEnding": "2017-02-28", "reportedCurrency": "USD", "operatingCashflow": "118900000", "paymentsForOperatingActivities": "None", "proceedsFromOperatingActivities": "None", "changeInOperatingLiabilities": "None", "changeInOperatingAssets": "None", "depreciationDepletionAndAmortization": "28600000", "capitalExpenditures": "6786000", "changeInReceivables": "-21763000", "changeInInventory": "18381000", "profitLoss": "None", "cashflowFromInvestment": "-18307000", "cashflowFromFinancing": "-100600000", "proceedsFromRepaymentsOfShortTermDebt": "None", "paymentsForRepurchaseOfCommonStock": "None", "paymentsForRepurchaseOfEquity": "None", "paymentsForRepurchaseOfPreferredStock": "None", "dividendPayout": "30500000", "dividendPayoutCommonStock": "30500000", "dividendPayoutPreferredStock": "None", "proceedsFromIssuanceOfCommonStock": "None", "proceedsFromIssuanceOfLongTermDebtAndCapitalSecuritiesNet": "None", "proceedsFromIssuanceOfPreferredStock": "None", "proceedsFromRepurchaseOfEquity": "-62600000", "proceedsFromSaleOfTreasuryStock": "None", "changeInCashAndCashEquivalents": "-88130000", "changeInExchangeRate": "None", "netIncome": "-80100000"}, {"fiscalDateEnding": "2016-11-30", "reportedCurrency": "USD", "operatingCashflow": "121400000", "paymentsForOperatingActivities": "None", "proceedsFromOperatingActivities": "None", "changeInOperatingLiabilities": "None", "changeInOperatingAssets": "None", "depreciationDepletionAndAmortization": "30000000", "capitalExpenditures": "13347000", "changeInReceivables": "26811000", "changeInInventory": "3710000", "profitLoss": "None", "cashflowFromInvestment": "44257000", "cashflowFromFinancing": "-80500000", "proceedsFromRepaymentsOfShortTermDebt": "None", "paymentsForRepurchaseOfCommonStock": "None", "paymentsForRepurchaseOfEquity": "None", "paymentsForRepurchaseOfPreferredStock": "None", "dividendPayout": "30700000", "dividendPayoutCommonStock": "30700000", "dividendPayoutPreferredStock": "None", "proceedsFromIssuanceOfCommonStock": "None", "proceedsFromIssuanceOfLongTermDebtAndCapitalSecuritiesNet": "None", "proceedsFromIssuanceOfPreferredStock": "None", "proceedsFromRepurchaseOfEquity": "-45300000", "proceedsFromSaleOfTreasuryStock": "None", "changeInCashAndCashEquivalents": "62504000", "changeInExchangeRate": "None", "netIncome": "72600000"}, {"fiscalDateEnding": "2016-08-31", "reportedCurrency": "USD", "operatingCashflow": "59300000", "paymentsForOperatingActivities": "None", "proceedsFromOperatingActivities": "None", "changeInOperatingLiabilities": "None", "changeInOperatingAssets": "None", "depreciationDepletionAndAmortization": "29900000", "capitalExpenditures": "17835000", "changeInReceivables": "-13512000", "changeInInventory": "-6364000", "profitLoss": "None", "cashflowFromInvestment": "-8082000", "cashflowFromFinancing": "-35400000", "proceedsFromRepaymentsOfShortTermDebt": "None", "paymentsForRepurchaseOfCommonStock": "None", "paymentsForRepurchaseOfEquity": "None", "paymentsForRepurchaseOfPreferredStock": "None", "dividendPayout": "30600000", "dividendPayoutCommonStock": "30600000", "dividendPayoutPreferredStock": "None", "proceedsFromIssuanceOfCommonStock": "None", "proceedsFromIssuanceOfLongTermDebtAndCapitalSecuritiesNet": "None", "proceedsFromIssuanceOfPreferredStock": "None", "proceedsFromRepurchaseOfEquity": "300000", "proceedsFromSaleOfTreasuryStock": "None", "changeInCashAndCashEquivalents": "32836000", "changeInExchangeRate": "None", "netIncome": "51300000"}, {"fiscalDateEnding": "2016-05-31", "reportedCurrency": "USD", "operatingCashflow": "26600000", "paymentsForOperatingActivities": "None", "proceedsFromOperatingActivities": "None", "changeInOperatingLiabilities": "None", "changeInOperatingAssets": "None", "depreciationDepletionAndAmortization": "28200000", "capitalExpenditures": "16986000", "changeInReceivables": "-68025000", "changeInInventory": "12903000", "profitLoss": "None", "cashflowFromInvestment": "-36933000", "cashflowFromFinancing": "-167800000", "proceedsFromRepaymentsOfShortTermDebt": "None", "paymentsForRepurchaseOfCommonStock": "None", "paymentsForRepurchaseOfEquity": "None", "paymentsForRepurchaseOfPreferredStock": "None", "dividendPayout": "31200000", "dividendPayoutCommonStock": "31200000", "dividendPayoutPreferredStock": "None", "proceedsFromIssuanceOfCommonStock": "None", "proceedsFromIssuanceOfLongTermDebtAndCapitalSecuritiesNet": "None", "proceedsFromIssuanceOfPreferredStock": "None", "proceedsFromRepurchaseOfEquity": "-131100000", "proceedsFromSaleOfTreasuryStock": "None", "changeInCashAndCashEquivalents": "-61470000", "changeInExchangeRate": "None", "netIncome": "-771900000"}]}